dl4ds/__init__.py
dl4ds/app.py
dl4ds/dataloader.py
dl4ds/inference.py
dl4ds/losses.py
dl4ds/metrics.py
dl4ds/preprocessing.py
dl4ds/utils.py
dl4ds/models/__init__.py
dl4ds/models/blocks.py
dl4ds/models/discriminator.py
dl4ds/models/sp_postups.py
dl4ds/models/sp_preups.py
dl4ds/models/spt_postups.py
dl4ds/models/spt_preups.py
dl4ds/training/__init__.py
dl4ds/training/base.py
dl4ds/training/cgan.py
dl4ds/training/supervised.py
dl4ds-1.8.0.dist-info/LICENSE
dl4ds-1.8.0.dist-info/METADATA
dl4ds-1.8.0.dist-info/WHEEL
dl4ds-1.8.0.dist-info/top_level.txt
dl4ds-1.8.0.dist-info/RECORD
