Metadata-Version: 2.1
Name: dl4ds
Version: 1.8.0
Summary: Deep Learning for empirical DownScaling
Home-page: https://github.com/carlgogo/dl4ds
Author: Carlos Alberto Gomez Gonzalez
Author-email: carlos.gomez@bsc.es
License: Apache v2.0
Keywords: deep learning,downscaling,super-resolution,neural networks,Earth data,EO
Classifier: Intended Audience :: Science/Research
Classifier: Operating System :: POSIX :: Linux
Classifier: Natural Language :: English
Classifier: License :: OSI Approved :: Apache Software License
Classifier: Programming Language :: Python
Classifier: Programming Language :: Python :: 3
Classifier: Programming Language :: Python :: 3.7
Classifier: Topic :: Scientific/Engineering
License-File: LICENSE
Requires-Dist: numpy
Requires-Dist: scipy
Requires-Dist: matplotlib
Requires-Dist: xarray
Requires-Dist: ecubevis
Requires-Dist: tensorflow
Requires-Dist: sklearn
Requires-Dist: opencv-python
Requires-Dist: joblib
Requires-Dist: seaborn
Requires-Dist: absl-py
Provides-Extra: horovod
Requires-Dist: horovod ; extra == 'horovod'
